{
  "generated_at": "2026-07-17T08:07:56+00:00",
  "dataset": "../sample-data/semiconductor_rag_eval_development.json",
  "top_k": 3,
  "first_scenario_is_baseline": "dense_single",
  "note": "hybrid scenarios use deterministic weighted dense/lexical/facet fusion; they do not use a cross-encoder reranker",
  "scenarios": {
    "dense_single": {
      "configuration": {
        "RAG_HYBRID_ENABLED": "false",
        "RAG_MULTI_QUERY_ENABLED": "false",
        "RAG_NEIGHBOR_ENABLED": "false"
      },
      "return_code": 1,
      "summary": {
        "passed": 3,
        "total": 20,
        "positive_hits": 16,
        "positive_total": 16,
        "negative_rejections": 1,
        "negative_total": 4,
        "gold_source_hits": 10,
        "gold_source_total": 16,
        "mrr": 0.59375,
        "ndcg_at_k": 0.554098,
        "mean_group_coverage": 0.526044,
        "average_latency_ms": 486.9,
        "first_case_latency_ms": 896.1,
        "p50_latency_ms": 460.6,
        "p95_latency_ms": 535.3,
        "max_latency_ms": 896.1,
        "total_neighbors": 0,
        "average_query_variants": 1.0
      },
      "report": "dense_single.json",
      "delta_vs_first": {
        "passed": 0,
        "mrr": 0.0,
        "ndcg_at_k": 0.0,
        "p95_latency_ms": 0.0
      }
    },
    "dense_multi": {
      "configuration": {
        "RAG_HYBRID_ENABLED": "false",
        "RAG_MULTI_QUERY_ENABLED": "true",
        "RAG_NEIGHBOR_ENABLED": "false"
      },
      "return_code": 1,
      "summary": {
        "passed": 7,
        "total": 20,
        "positive_hits": 16,
        "positive_total": 16,
        "negative_rejections": 0,
        "negative_total": 4,
        "gold_source_hits": 12,
        "gold_source_total": 16,
        "mrr": 0.614583,
        "ndcg_at_k": 0.603853,
        "mean_group_coverage": 0.733337,
        "average_latency_ms": 561.3,
        "first_case_latency_ms": 1287.7,
        "p50_latency_ms": 525.2,
        "p95_latency_ms": 703.0,
        "max_latency_ms": 1287.7,
        "total_neighbors": 0,
        "average_query_variants": 4.25
      },
      "report": "dense_multi.json",
      "delta_vs_first": {
        "passed": 4,
        "mrr": 0.020833,
        "ndcg_at_k": 0.049755,
        "p95_latency_ms": 167.7
      }
    },
    "hybrid_multi": {
      "configuration": {
        "RAG_HYBRID_ENABLED": "true",
        "RAG_MULTI_QUERY_ENABLED": "true",
        "RAG_NEIGHBOR_ENABLED": "false"
      },
      "return_code": 0,
      "summary": {
        "passed": 20,
        "total": 20,
        "positive_hits": 16,
        "positive_total": 16,
        "negative_rejections": 4,
        "negative_total": 4,
        "gold_source_hits": 16,
        "gold_source_total": 16,
        "mrr": 0.708333,
        "ndcg_at_k": 0.718531,
        "mean_group_coverage": 1.0,
        "average_latency_ms": 1321.1,
        "first_case_latency_ms": 3817.5,
        "p50_latency_ms": 1072.5,
        "p95_latency_ms": 2788.6,
        "max_latency_ms": 3817.5,
        "total_neighbors": 0,
        "average_query_variants": 4.05
      },
      "report": "hybrid_multi.json",
      "delta_vs_first": {
        "passed": 17,
        "mrr": 0.114583,
        "ndcg_at_k": 0.164433,
        "p95_latency_ms": 2253.3
      }
    },
    "hybrid_multi_neighbor": {
      "configuration": {
        "RAG_HYBRID_ENABLED": "true",
        "RAG_MULTI_QUERY_ENABLED": "true",
        "RAG_NEIGHBOR_ENABLED": "true"
      },
      "return_code": 0,
      "summary": {
        "passed": 20,
        "total": 20,
        "positive_hits": 16,
        "positive_total": 16,
        "negative_rejections": 4,
        "negative_total": 4,
        "gold_source_hits": 16,
        "gold_source_total": 16,
        "mrr": 0.708333,
        "ndcg_at_k": 0.718531,
        "mean_group_coverage": 1.0,
        "average_latency_ms": 1368.5,
        "first_case_latency_ms": 4035.2,
        "p50_latency_ms": 1136.4,
        "p95_latency_ms": 3251.0,
        "max_latency_ms": 4035.2,
        "total_neighbors": 9,
        "average_query_variants": 4.05
      },
      "report": "hybrid_multi_neighbor.json",
      "delta_vs_first": {
        "passed": 17,
        "mrr": 0.114583,
        "ndcg_at_k": 0.164433,
        "p95_latency_ms": 2715.7
      }
    }
  },
  "execution_errors": []
}
